pytranscoding/__init__.py
pytranscoding/helpers.py
pytranscoding/mappers.py
pytranscoding/models.py
pytranscoding/pytranscoding.py
pytranscoding/cli/__init__.py
pytranscoding/cli/config.py
pytranscoding/cli/convert.py
pytranscoding/cli/main.py
pytranscoding/cli/wingdbstub.py
pytranscoding/cli/workspace.py
pytranscoding-0.1.3.dist-info/AUTHORS.rst
pytranscoding-0.1.3.dist-info/LICENSE
pytranscoding-0.1.3.dist-info/METADATA
pytranscoding-0.1.3.dist-info/WHEEL
pytranscoding-0.1.3.dist-info/entry_points.txt
pytranscoding-0.1.3.dist-info/top_level.txt
pytranscoding-0.1.3.dist-info/RECORD
