Metadata-Version: 2.1
Name: pytranscoding
Version: 0.1.3
Summary: Python Transcoding Tools
Home-page: https://github.com/asterio.gonzalez/pytranscoding
Author: Asterio Gonzalez
Author-email: asterio.gonzalez@gmail.com
License: MIT license
Keywords: pytranscoding
Platform: UNKNOWN
Classifier: Development Status :: 2 - Pre-Alpha
Classifier: Intended Audience :: Developers
Classifier: License :: OSI Approved :: MIT License
Classifier: Natural Language :: English
Classifier: Programming Language :: Python :: 3
Classifier: Programming Language :: Python :: 3.9
Classifier: Programming Language :: Python :: 3.10
Classifier: Programming Language :: Python :: 3.11
Requires-Python: >=3.6
License-File: LICENSE
License-File: AUTHORS.rst
Requires-Dist: Click (>=7.1.2)
Requires-Dist: agptools
Requires-Dist: boltons
Requires-Dist: ffmpeg-python
Requires-Dist: pydantic
Requires-Dist: surrealdb
Requires-Dist: uvloop
